{
  "backendUrl": "https://widget.numbero.org",
  "assistantId": "assistant_bpo_ai",
  "badgeText": "BPO AI",
  "title": "Customer support, amplified.",
  "subtitle": "Voice-first automation for contact centers. Start a demo call to experience a live AI agent.",
  "startButtonText": "Start Demo Call",
  "endButtonText": "End Call",
  "statusReady": "Ready to serve",
  "statusConnected": "On call with customer",
  "greetingText": "Welcome. How can I assist with this customer's request?",
  "connectingText": "Connecting to AI agent...",
  "connectedText": "Live. You may speak now.",
  "agentReadyText": "Agent ready to take the call.",
  "disconnectedText": "Call ended",
  "connectionFailedText": "Unable to connect",
  "initializingMicText": "Initializing microphone...",
  "initializingDevicesText": "Initializing devices...",
  "userTranscriptPrefix": "You",
  "agentTranscriptPrefix": "Agent",
  "logoUrl": "/images/logo.png",
  "logoAlt": "LYRIQ",
  "fabAriaLabel": "Voice assistant",
  "scriptPath": "/widget-bundle.js",
  "autoOpen": true,
  "autoOpenDelayMs": 1500,
  "primaryColor": "#7c3aed",
  "accentColor": "#a855f7",
  "endButtonColor": "#EF4444",
  "successColor": "#10B981",
  "panelBgColor": "rgba(15, 10, 30, 0.85)",
  "titleColor": "#f1f5f9"
}
